outrank/__init__.py
outrank/__main__.py
outrank/core_ranking.py
outrank/core_selftest.py
outrank/core_utils.py
outrank/task_generators.py
outrank/task_instance_ranking.py
outrank/task_ranking.py
outrank/task_selftest.py
outrank/task_summary.py
outrank/task_visualization.py
outrank/algorithms/__init__.py
outrank/algorithms/importance_estimator.py
outrank/algorithms/feature_ranking/__init__.py
outrank/algorithms/feature_ranking/ranking_cov_alignment.py
outrank/algorithms/feature_ranking/ranking_mi_numba.py
outrank/algorithms/sketches/__init__.py
outrank/algorithms/sketches/counting_cms.py
outrank/algorithms/sketches/counting_counters_ordinary.py
outrank/algorithms/sketches/counting_ultiloglog.py
outrank/algorithms/synthetic_data_generators/__init__.py
outrank/algorithms/synthetic_data_generators/cc_generator.py
outrank/algorithms/synthetic_data_generators/generator_naive.py
outrank/feature_transformations/__init__.py
outrank/feature_transformations/ranking_transformers.py
outrank/feature_transformations/feature_transformer_vault/__init__.py
outrank/feature_transformations/feature_transformer_vault/default_transformers.py
outrank/feature_transformations/feature_transformer_vault/fw_transformers.py
outrank/visualizations/__init__.py
outrank/visualizations/ranking_visualization.py
outrank-0.97.5.dist-info/LICENSE.md
outrank-0.97.5.dist-info/METADATA
outrank-0.97.5.dist-info/WHEEL
outrank-0.97.5.dist-info/entry_points.txt
outrank-0.97.5.dist-info/top_level.txt
outrank-0.97.5.dist-info/zip-safe
outrank-0.97.5.dist-info/RECORD
