Metadata-Version: 2.1
Name: outrank
Version: 0.97.5
Summary: OutRank: Feature ranking for massive sparse data sets.
Home-page: https://github.com/outbrain/outrank
Author: Research Infra (Outbrain); Blaz Skrlj led the development of this project
License: BSD
License-File: LICENSE.md
Requires-Dist: flake8>=6.1.0
Requires-Dist: matplotlib>=3.7.2
Requires-Dist: numba>=0.55.1
Requires-Dist: numpy>=1.21.6
Requires-Dist: pandas>=1.3.1
Requires-Dist: pathos>=0.2.9
Requires-Dist: pre-commit>=3.4.0
Requires-Dist: scikit-learn>=0.24.1
Requires-Dist: scipy>=1.8.1
Requires-Dist: seaborn>=0.12
Requires-Dist: tqdm>=4.63.0
Requires-Dist: xxhash>=3.0.0
